{"v":4,"entries":{"graph-canvas--default":{"type":"story","id":"graph-canvas--default","name":"Default","title":"Graph/Canvas","importPath":"./src/stories/canvas/canvas.stories.ts","tags":["story"]},"example-page--logged-out":{"type":"story","id":"example-page--logged-out","name":"Logged Out","title":"Example/Page","importPath":"./src/stories/page/Page.stories.ts","tags":["story"]},"example-page--logged-in":{"type":"story","id":"example-page--logged-in","name":"Logged In","title":"Example/Page","importPath":"./src/stories/page/Page.stories.ts","tags":["play-fn","story"]},"structures-nodes--default":{"type":"story","id":"structures-nodes--default","name":"Default","title":"Structures/nodes","importPath":"./src/stories/structures/nodes.stories.ts","tags":["story"]},"test-canvases-canvas-draggable--create-page":{"type":"story","id":"test-canvases-canvas-draggable--create-page","name":"Create Page","title":"Test Canvases/canvas-draggable","importPath":"./src/stories/test_canvases/canvas-draggable.stories.ts","tags":["story"]},"test-canvases-canvas-draggable--default":{"type":"story","id":"test-canvases-canvas-draggable--default","name":"Default","title":"Test Canvases/canvas-draggable","importPath":"./src/stories/test_canvases/canvas-draggable.stories.ts","tags":["story"]},"test-canvases-node-interaction--create-page":{"type":"story","id":"test-canvases-node-interaction--create-page","name":"Create Page","title":"Test Canvases/node-interaction","importPath":"./src/stories/test_canvases/canvas-node-interaction.stories.ts","tags":["story"]},"test-canvases-node-interaction--default":{"type":"story","id":"test-canvases-node-interaction--default","name":"Default","title":"Test Canvases/node-interaction","importPath":"./src/stories/test_canvases/canvas-node-interaction.stories.ts","tags":["story"]},"test-canvases-canvas1--create-page":{"type":"story","id":"test-canvases-canvas1--create-page","name":"Create Page","title":"Test Canvases/canvas1","importPath":"./src/stories/test_canvases/canvas1.stories.ts","tags":["story"]},"test-canvases-canvas1--default":{"type":"story","id":"test-canvases-canvas1--default","name":"Default","title":"Test Canvases/canvas1","importPath":"./src/stories/test_canvases/canvas1.stories.ts","tags":["story"]}}}
